CryptoPlus/Protocol.py
CryptoPlus/PublicKey.py
CryptoPlus/__init__.py
CryptoPlus/testvectors.py
CryptoPlus/Cipher/AES.py
CryptoPlus/Cipher/ARC2.py
CryptoPlus/Cipher/Blowfish.py
CryptoPlus/Cipher/CAST.py
CryptoPlus/Cipher/DES.py
CryptoPlus/Cipher/DES3.py
CryptoPlus/Cipher/IDEA.py
CryptoPlus/Cipher/RC5.py
CryptoPlus/Cipher/__init__.py
CryptoPlus/Cipher/blockcipher.py
CryptoPlus/Cipher/pyDes.py
CryptoPlus/Cipher/pyblowfish.py
CryptoPlus/Cipher/pypresent.py
CryptoPlus/Cipher/pyserpent.py
CryptoPlus/Cipher/python_AES.py
CryptoPlus/Cipher/python_Blowfish.py
CryptoPlus/Cipher/python_DES.py
CryptoPlus/Cipher/python_DES3.py
CryptoPlus/Cipher/python_PRESENT.py
CryptoPlus/Cipher/python_Rijndael.py
CryptoPlus/Cipher/python_Serpent.py
CryptoPlus/Cipher/python_Twofish.py
CryptoPlus/Cipher/pytwofish.py
CryptoPlus/Cipher/rijndael.py
CryptoPlus/Hash/RIPEMD.py
CryptoPlus/Hash/__init__.py
CryptoPlus/Hash/pymd5.py
CryptoPlus/Hash/pypbkdf2.py
CryptoPlus/Hash/pyradiogatun.py
CryptoPlus/Hash/pysha.py
CryptoPlus/Hash/pysha224.py
CryptoPlus/Hash/pysha256.py
CryptoPlus/Hash/pysha384.py
CryptoPlus/Hash/pysha512.py
CryptoPlus/Hash/python_MD5.py
CryptoPlus/Hash/python_PBKDF2.py
CryptoPlus/Hash/python_RadioGatun.py
CryptoPlus/Hash/python_SHA.py
CryptoPlus/Hash/python_SHA224.py
CryptoPlus/Hash/python_SHA256.py
CryptoPlus/Hash/python_SHA384.py
CryptoPlus/Hash/python_SHA512.py
CryptoPlus/Hash/python_whirlpool.py
CryptoPlus/Hash/pywhirlpool.py
CryptoPlus/Random/Fortuna.py
CryptoPlus/Random/OSRNG.py
CryptoPlus/Random/__init__.py
CryptoPlus/SelfTest/__init__.py
CryptoPlus/SelfTest/st_common.py
CryptoPlus/SelfTest/Cipher/__init__.py
CryptoPlus/SelfTest/Cipher/common.py
CryptoPlus/SelfTest/Cipher/test_AES.py
CryptoPlus/SelfTest/Cipher/test_ARC2.py
CryptoPlus/SelfTest/Cipher/test_ARC4.py
CryptoPlus/SelfTest/Cipher/test_Blowfish.py
CryptoPlus/SelfTest/Cipher/test_CAST.py
CryptoPlus/SelfTest/Cipher/test_DES.py
pycryptoplus-0.0.1.dist-info/METADATA
pycryptoplus-0.0.1.dist-info/RECORD
pycryptoplus-0.0.1.dist-info/WHEEL
pycryptoplus-0.0.1.dist-info/top_level.txt
